{"name": "ATLAS - Agenda Check (1min)", "nodes": [{"id": "n1", "name": "A cada 1 minuto", "type": "n8n-nodes-base.scheduleTrigger", "typeVersion": 1.1, "position": [240, 300], "parameters": {"rule": {"interval": [{"field": "minutes", "minutesInterval": 1}]}}}, {"id": "n2", "name": "GET Agenda Check", "type": "n8n-nodes-base.httpRequest", "typeVersion": 4.2, "position": [460, 300], "parameters": {"url": "https://atlas-m3wb.onrender.com/v1/reminders/check", "options": {"timeout": 15000}}}, {"id": "n3", "name": "Tem Lembretes?", "type": "n8n-nodes-base.if", "typeVersion": 2, "position": [680, 300], "parameters": {"conditions": {"options": {"caseSensitive": true, "leftValue": "", "typeValidation": "strict"}, "conditions": [{"id": "c1", "leftValue": "={{ $json.count }}", "rightValue": 0, "operator": {"type": "number", "operation": "gt"}}], "combinator": "and"}, "options": {}}}, {"id": "n4", "name": "Sem Lembretes", "type": "n8n-nodes-base.noOp", "typeVersion": 1, "position": [900, 460], "parameters": {}}, {"id": "n5", "name": "Dividir Lembretes", "type": "n8n-nodes-base.code", "typeVersion": 2, "position": [900, 300], "parameters": {"jsCode": "return $input.first().json.reminders.map(r => ({ json: r }));"}}, {"id": "n6", "name": "Pegar Conversa", "type": "n8n-nodes-base.code", "typeVersion": 2, "position": [1120, 300], "parameters": {"mode": "runOnceForEachItem", "jsCode": "const phone = $input.item.json.phone;\nconst message = $input.item.json.message;\n\nconst searchData = await this.helpers.httpRequest({\n  method: \"GET\",\n  url: \"https://chatwood.rodrigobrito.cloud/api/v1/accounts/1/contacts/search\",\n  qs: { q: phone },\n  headers: { \"api_access_token\": \"KmFTvrjqvLuUSEQwAaUuJe4d\" }\n});\nconst contacts = searchData.payload || [];\nif (\\!contacts || contacts.length === 0) {\n  return { json: {} };\n}\nconst contactId = contacts[0].id;\n\nconst convData = await this.helpers.httpRequest({\n  method: \"GET\",\n  url: \"https://chatwood.rodrigobrito.cloud/api/v1/accounts/1/contacts/\" + contactId + \"/conversations\",\n  headers: { \"api_access_token\": \"KmFTvrjqvLuUSEQwAaUuJe4d\" }\n});\nconst conversations = convData.payload || [];\nconst activeConv = conversations.find(c => c.status === \"open\") || conversations[0];\nif (\\!activeConv) {\n  return { json: {} };\n}\nreturn {\n  json: {\n    conversation_id: activeConv.id,\n    message: message\n  }\n};"}}, {"id": "n7", "name": "Enviar Mensagem Chatwoot", "type": "n8n-nodes-base.httpRequest", "typeVersion": 4.2, "position": [1340, 300], "parameters": {"method": "POST", "url": "=https://chatwood.rodrigobrito.cloud/api/v1/accounts/1/conversations/{{ $json.conversation_id }}/messages", "sendHeaders": true, "headerParameters": {"parameters": [{"name": "api_access_token", "value": "KmFTvrjqvLuUSEQwAaUuJe4d"}]}, "sendBody": true, "specifyBody": "json", "jsonBody": "={{ JSON.stringify({ content: $json.message, message_type: \"outgoing\", private: false }) }}", "options": {}}}], "connections": {"A cada 1 minuto": {"main": [[{"node": "GET Agenda Check", "type": "main", "index": 0}]]}, "GET Agenda Check": {"main": [[{"node": "Tem Lembretes?", "type": "main", "index": 0}]]}, "Tem Lembretes?": {"main": [[{"node": "Dividir Lembretes", "type": "main", "index": 0}], [{"node": "Sem Lembretes", "type": "main", "index": 0}]]}, "Dividir Lembretes": {"main": [[{"node": "Pegar Conversa", "type": "main", "index": 0}]]}, "Pegar Conversa": {"main": [[{"node": "Enviar Mensagem Chatwoot", "type": "main", "index": 0}]]}}, "settings": {"executionOrder": "v1"}}